Workbook

Sheet OVERVIEW
A1: SITE NAME: | E1: MAX DISCOUNT8 | H1: 0.15 | I1: DIRECT SERVICES DISCOUNT APPLIED8 | J1: 0
A2: SITE ID:
A3: DIRECT SERVICES | I3: NOTES
B4: COVER TYPE | C4: VISITS | D4: PRICE | E4: SELL PRICE | F4: 0 | G4: =H1 -> 0.15 | H4: LABOUR MARGIN
A5: Annual Fire Alarm Maintenance | B5: Standard | C5: 2 | D5: =IF('FIRE & LIGHTS'!$M$11=0,0,'FIRE & LIGHTS'!U21) -> 0 | E5: =D5-(D5*$J$1) -> 0 | H5: =1-(OVERVIEW!$K$5/('FIRE & LIGHTS'!$Q$3-(OVERVIEW!$J$1*'FIRE & LIGHTS'!$Q$3))) -> 0.59831169 | K5: 30.93 | L5: Engineer Hourly Cost
A6: Annual Fire Alarm Maintenance | B6: Standard | C6: 4 | D6: =IF('FIRE & LIGHTS'!$M$11=0,0,'FIRE & LIGHTS'!U22) -> 0 | E6: =D6-(D6*$J$1) -> 0 | H6: =1-(OVERVIEW!$K$5/('FIRE & LIGHTS'!$Q$3-(OVERVIEW!$J$1*'FIRE & LIGHTS'!$Q$3))) -> 0.59831169 | K6: 25.95 | L6: CDO Hourly Cost
A7: Annual Fire Alarm Maintenance | B7: Comprehensive | C7: 2 | D7: =IF('FIRE & LIGHTS'!$M$11=0,0,'FIRE & LIGHTS'!U23) -> 0 | E7: =D7-(D7*$J$1) -> 0 | H7: =1-(OVERVIEW!$K$5/('FIRE & LIGHTS'!$Q$3-(OVERVIEW!$J$1*'FIRE & LIGHTS'!$Q$3))) -> 0.59831169 | K7: =K6*7.5/17.5 -> 11.121429 | L7: Cost per weekly test (17.5 tests)
A8: Annual Fire Alarm Maintenance | B8: Comprehensive | C8: 4 | D8: =IF('FIRE & LIGHTS'!$M$11=0,0,'FIRE & LIGHTS'!U24) -> 0 | E8: =D8-(D8*$J$1) -> 0 | H8: =1-(OVERVIEW!$K$5/('FIRE & LIGHTS'!$Q$3-(OVERVIEW!$J$1*'FIRE & LIGHTS'!$Q$3))) -> 0.59831169
A9: Fire Alarm Weekly Testing | C9: ='FIRE & LIGHTS'!U14 -> 0 | D9: ='FIRE & LIGHTS'!U26 -> 0 | E9: =D9-(D9*$J$1) -> 0 | H9: =1-(K7/'FIRE & LIGHTS'!U13) -> 0.59558442 | I9: Based upon completing 17.5 tests (AVG) per day
A10: Annual Emergency Lighting Maintenance | B10: Standard | C10: 1 | D10: ='FIRE & LIGHTS'!U28 -> 0 | E10: =D10-(D10*$J$1) -> 0 | H10: Inc... | I10: Includes 20% "1 visit" discount
A11: Monthly Emergency Lighting Testing | B11: N/A | C11: ='FIRE & LIGHTS'!U16 -> 0 | D11: ='FIRE & LIGHTS'!U30 -> 0 | E11: =D11-(D11*$J$1) -> 0 | H11: =1-(K6/('FIRE & LIGHTS'!U15/3*4)) -> 0.60280612 | I11: Based upon 45 mins per test
A12: Annual Intruder Alarm Maintenance | B12: =IF(INTRUDER!R8=1,("Platinum"),("Standard")) -> Standard | C12: =INTRUDER!S3 -> 2 | D12: =INTRUDER!T8 -> 0 | E12: =D12-(D12*$J$1) -> 0 | H12: =1-(OVERVIEW!K5/(INTRUDER!Q3-INTRUDER!Q3*OVERVIEW!J1)) -> 0.59831169
A13: Annual CCTV Maintenance | C13: =CCTV!P3 -> 1 | D13: =CCTV!Q9 -> 0 | E13: =D13-(D13*$J$1) -> 0 | H13: =1-(K5/(CCTV!N3-CCTV!N3*OVERVIEW!J1)) -> 0.59831169
A14: Annual Access Control Maintenance | C14: =ACCESS!H3 -> 1 | D14: =ACCESS!I9 -> 0 | E14: =D14-(D14*$J$1) -> 0 | H14: =1-(K5/ACCESS!F3-ACCESS!F3*OVERVIEW!J1) -> 0.59831169
A15: Annual Damper Maintenance | C15: =DAMPERS!G3 -> 1 | D15: =DAMPERS!H9 -> 0 | E15: =D15-(D15*$J$1) -> 0 | H15: =1-(K6*2/DAMPERS!E3-DAMPERS!E3*OVERVIEW!J1) -> 0.50096154
A16: MONITORING | I16: MONITORING DISCOUNT APPLIED8 | J16: 0
D17: PRICE | E17: SELL PRICE | F17: 0 | G17: =H15 -> 0.50096154 | H17: MARGIN | I17: NOTES
A18: Annual Fire Alarm Monitoring | D18: =MONITORING!T4 -> 0 | E18: =D18-(D18*$J$16) -> 0 | H18: =MONITORING!Y3 -> 0% | K18: =MONITORING!Q6 -> 0 | L18: Fire Monitoring Cost
A19: Annual Intruder Alarm Monitoring | D19: =MONITORING!T7 -> 0 | E19: =D19-(D19*$J$16) -> 0 | K19: =MONITORING!Q9 -> 0 | L19: Intruder Monitoring Cost
A20: Annual CCTV Monitoring | D20: =MONITORING!T11 -> 0 | E20: =D20-(D20*$J$16) -> 0 | K20: =MONITORING!Q11 -> 0 | L20: CCTV Monitoring Cost
A21: OTHER SUB-CONTRACTED SERVICES: | E21: SUB-CONTRACT MARK-UP8 | H21: 0.5
A22: Service Offered: | B22: COVER TYPE | C22: VISITS | D22: PRICE | E22: SELL PRICE | F22: 0 | G22: =H20 -> 0 | H22: MARGIN | I22: NOTES
D23: 0 | E23: 0 | H23: =IF(D23=0,(0),(1-(D23/E23))) -> 0
D24: 0 | E24: =D24+(D24*$H$21) -> 0 | H24: =IF(D24=0,(0),(1-(D24/E24))) -> 0
D25: 0 | E25: =D25+(D25*$H$21) -> 0 | H25: =IF(D25=0,(0),(1-(D25/E25))) -> 0
D26: 0 | E26: =D26+(D26*$H$21) -> 0 | H26: =IF(D26=0,(0),(1-(D26/E26))) -> 0
D27: 0 | E27: =D27+(D27*$H$21) -> 0 | H27: =IF(D27=0,(0),(1-(D27/E27))) -> 0
D28: 0 | E28: =D28+(D28*$H$21) -> 0 | H28: =IF(D28=0,(0),(1-(D28/E28))) -> 0
D29: 0 | E29: =D29+(D29*$H$21) -> 0 | H29: =IF(D29=0,(0),(1-(D29/E29))) -> 0
B30: Sub-Contract Sub-Total | D30: =SUM(D23:D29) -> 0 | E30: =SUM(E23:E29) -> 0 | H30: =IF(D30=0,(0),(1-(D30/E30))) -> 0
D32: TOTAL SALE | E32: =SUM(E5:E29) -> 0 | J32: SF1619: Issue 02

Sheet FIRE & LIGHTS
U1: =IF($N$8+$O$8=0,0,IF((20+$N$8*60+$O$8+$B$4)*$C$4*$A$4/60<=(S3-1),S3,IF(AND((20+$N$8*60+$O$8)*$C$4*$A$4/60<=139,SUM($C$8:$M$8)>0),S3,IF(SUM($C$8:$M$8)=0,(20+$N$8*60+$O$8+$B$4)*$C$4*$A$4/60,(20+$N$8*60+$O$8)*$C$4*$A$4/60)))) -> 0
Q2: SLR | R2: MIN Fire Price | S2: MIN EL Price | T2: Travel
Q3: 77 | R3: 199 | S3: 99 | T3: 20 | U3: 2
A4: =Q3 -> 77 | B4: =T3 -> 20 | C4: =U3 -> 2 | D4: 4 | E4: COMP | F4: 0.5
A6: FIRE ALARM & EMERGENCY LIGHTING MAINTENANCE CALCULATOR | W6: LABOUR MARGIN
A7: Site ID | B7: Site Name | C7: Control Panel | D7: Repeater | E7: Power Supply Units | F7: Manual Call Points | G7: Smoke Detectors | H7: Heat Detectors | I7: Beams | J7: Mains Interfaces | K7: Sounders | L7: Network | M7: Remote Signalling | N7: Central Battery Unit | O7: Luminaires | Q7: Fire Alarm 2 Visits STANDARD | R7: Fire Alarm 4 Visits STANDARD | S7: Fire Alarm 2 Visits COMPREHENSIVE | T7: Fire Alarm 4 Visits COMPREHENSIVE | U7: Emergency Lights 1 VISIT STANDARD | W7: =1-(OVERVIEW!K5/'FIRE & LIGHTS'!Q3) -> 0.59831169
A8: =OVERVIEW!B2 -> 0 | B8: =OVERVIEW!B1 -> 0 | C8: 0 | D8: 0 | E8: 0 | F8: 0 | G8: 0 | H8: 0 | I8: 0 | J8: 0 | K8: 0 | L8: 0 | M8: 0 | N8: 0 | O8: 0 | Q8: =IF($Q$11<R3,($R$3),($Q$11)) -> 199 | R8: =IF(R11<(R3+2*B4/60*A4),(R3+2*B4/60*A4),(R11)) -> 250.33333 | S8: =S10 -> 298.5 | T8: =T10 -> 349.83333 | U8: =IF(U1<99,99,U1) -> 99
B9: MAJOR | C9: 30 | D9: 15 | E9: 15 | F9: 2 | G9: 2.5 | H9: 3.5 | I9: 15 | J9: 15 | K9: 0.5 | L9: 15 | M9: 15 | Q9: =((C8*C9+D8*D9+E8*E9+F8*F9+G8*G9+H8*H9+I8*I9+J8*J9+K8*K9+L8*L9+M8*M9)/60*$A$4)+(($B$4/60)*$A$4) -> 25.666667
B10: MINOR | C10: 1 | D10: 1 | E10: 1 | F10: 0.25 | G10: 0.15 | H10: 0.1 | I10: 1 | J10: 1 | K10: 1 | L10: 1 | M10: 1 | Q10: =((C9*C10*C8+D9*D10*D8+E9*E10*E8+F9*F10*F8+G9*G10*G8+H9*H10*H8+I9*I10*I8+J9*J10*J8+K9*K10*K8+L9*L10*L8+M9*M10*M8)/60*$A$4)+(($B$4/60)*$A$4) -> 25.666667 | S10: =Q8*(1+$F$4) -> 298.5 | T10: =S10-Q11+R11 -> 349.83333
M11: =SUM(C8:M8) -> 0 | O11: =SUM(N8:O8) -> 0 | Q11: =Q9+Q10 -> 51.333333 | R11: =Q9+Q10*3 -> 102.66667
A13: NOTES: | Q13: Weekly Test Price per Visit | U13: 27.5
Q14: Weekly Fire Testing - No of Visits | U14: 0 | V14: Enter "52" if required, "0" if not required
Q15: Monthly Lights Price per Visit | U15: 49 | V15: Based upon 45 minutes per test
Q16: Monthly Lights - No of Visits | U16: 0 | V16: Enter "11" if required, "0" if not required
Q18: SUMMARY
Q20: System | S20: Service | T20: No of Visits | U20: Price
Q21: Fire Alarm | S21: Standard | T21: 2 Visits | U21: =Q8 -> 199
Q22: Fire Alarm | S22: Standard | T22: 4 Visits | U22: =R8 -> 250.33333
Q23: Fire Alarm | S23: Comprehensive | T23: 2 Visits | U23: =S8 -> 298.5
Q24: Fire Alarm | S24: Comprehensive | T24: 4 Visits | U24: =T8 -> 349.83333
Q26: Fire Alarm | S26: Weekly Testing | T26: 52 Visits | U26: =U14*U13 -> 0
Q28: Emergency Lights | S28: Standard | T28: 1 Visit | U28: =U1 -> 0
Q30: Emergency Lights | S30: Monthly Testing | T30: 11 Visits | U30: =U16*U15 -> 0

Sheet INTRUDER
Q2: SLR | R2: Travel | S2: Visits | T2: MinPrice
Q3: 77 | R3: 20 | S3: 2 | T3: 99
A4: =Q3 -> 77 | B4: =R3 -> 20 | C4: =S3 -> 2 | D4: 1.5
A6: INTRUDER ALARM MAINTENANCE CALCULATOR | V6: LABOUR MARGIN
A7: Site ID | B7: Site Name | C7: Control Panel | D7: Remote Keypad | E7: Power Supply Units | F7: PIR/Dual Tec | G7: Door Contact | H7: Vibration Unit | I7: Roller Shutter Contact | J7: Personal Attack Button | K7: BGU | L7: Beams | M7: Audio Microphones | N7: Sounders | O7: Audio Verification C/U | P7: Remote Signalling | Q7: Standard Annual Intruder Maintenance Fee | R7: Platinum Contract ENTER "1" Below if REQ'D | S7: Out of Hours Working Required ENTER "1" Below if REQ'D | T7: Total to Quote | V7: =1-(OVERVIEW!K5/INTRUDER!Q3) -> 0.59831169
A8: =OVERVIEW!B2 -> 0 | B8: =OVERVIEW!B1 -> 0 | C8: 0 | D8: 0 | E8: 0 | F8: 0 | G8: 0 | H8: 0 | I8: 0 | J8: 0 | K8: 0 | L8: 0 | M8: 0 | N8: 0 | O8: 0 | P8: 0 | Q8: =IF(SUM(C8:P8)=0,(0),IF((((C8*C9*A4+D8*D9*A4+E8*E9*A4+F8*F9*A4+G8*G9*A4+H8*H9*A4+I8*I9*A4+J8*J9*A4+K8*K9*A4+L8*L9*A4+M8*M9*A4+N8*N9*A4+O8*O9*A4+P8*P9*A4)+(R3/60*Q3))*S3)<T3,(T3),(((C8*C9*A4+D8*D9*A4+E8*E9*A4+F8*F9*A4+G8*G9*A4+H8*H9*A4+I8*I9*A4+J8*J9*A4+K8*K9*A4+L8*L9*A4+M8*M9*A4+N8*N9*A4+O8*O9*A4+P8*P9*A4)+(R3/60*Q3))*S3))) -> 0 | R8: 0 | S8: 0 | T8: =S11 -> 0
C9: 0.33 | D9: 0.025 | E9: 0.167 | F9: 0.025 | G9: 0.025 | H9: 0.033 | I9: 0.025 | J9: 0.033 | K9: 0.033 | L9: 0.033 | M9: 0.083 | N9: 0.025 | O9: 0.166 | P9: 0.25 | R9: 0.5 | S9: 0.5
R10: =Q8*R9*R8 -> 0 | S10: =S8*S9*Q8 -> 0
A11: *** Remote signalling has been selected, please create a monitoring quotation *** | R11: TOTAL TO QUOTE: | S11: =Q8+R10+S10 -> 0
A13: NOTES:

Sheet CCTV
N2: SLR | O2: Travel | P2: Visits | Q2: MinPrice
N3: 77 | O3: 20 | P3: 1 | Q3: 99
A4: =N3 -> 77 | B4: =O3 -> 20 | C4: =P3 -> 1 | D4: 1.5
A6: CCTV MAINTENANCE CALCULATOR
C7: Control Equipment | G7: Cameras | K7: Other | N7: Pricing | S7: LABOUR MARGIN
A8: Site ID | B8: Site Name | C8: Monitor | D8: Remote Keypad c/w Joystick | E8: Remote PC Terminal | F8: DVR/NVR | G8: INTERNAL FIXED | H8: INTERNAL PTZ | I8: EXTERNAL FIXED | J8: EXTERNAL PTZ | K8: Redwall Detector | L8: Infared Lamp | M8: Camera Tower | N8: Standard CCTV Maintenance Fee | O8: Out of Hours Working Required ENTER "1" Below if REQ'D | P8: Select Access Equipment Or Enter COST Manually Below ***Ensure adjustment for banksman is included below*** | Q8: Total to Quote | S8: =1-(OVERVIEW!K5/CCTV!N3) -> 0.59831169
A9: =OVERVIEW!B2 -> 0 | B9: =OVERVIEW!B1 -> 0 | C9: 0 | D9: 0 | E9: 0 | F9: 0 | G9: 0 | H9: 0 | I9: 0 | J9: 0 | K9: 0 | L9: 0 | M9: 0 | N9: =IF(SUM(C9:M9)=0,(0),IF((((C9*C11*A4+D9*D11*A4+E9*E11*A4+F9*F11*A4+G9*G11*A4+H9*H11*A4+I9*I11*A4+J9*J11*A4+K9*K11*A4+L9*L11*A4+M9*M11*A4)+(O3/60*N3))*P3)<Q3,(Q3),(((C9*C11*A4+D9*D11*A4+E9*E11*A4+F9*F11*A4+G9*G11*A4+H9*H11*A4+I9*I11*A4+J9*J11*A4+K9*K11*A4+L9*L11*A4+M9*M11*A4)+(O3/60*N3))*P3))) -> 0 | O9: 0 | P9: =O23 -> 0 | Q9: =P13 -> 0
O10: Enter No of hours banksman required for here > | P10: 0
C11: 0.083 | D11: 0.25 | E11: 0.5 | F11: 0.75 | G11: 0.125 | H11: 0.25 | I11: 0.25 | J11: 0.5 | K11: 0.1 | L11: 0.1 | M11: 0.5 | O11: 0.5 | P11: 1.25 | Q11: =P10*N3/2 -> 0
O12: =N9*O11*O9 -> 0 | P12: =P11*P9 -> 0
O13: TOTAL TO QUOTE: | P13: =N9+O12+P12+Q11 -> 0
A15: NOTES:
N21: Access Equipment Lookup Table
N22: Selection | O22: 1 | P22: None | Q22: 1 | R22: 0
N23: Cost | O23: =VLOOKUP(O22,Q22:R26,2) -> 0 | P23: 15m Van Mount (Up to 1 Day) | Q23: 2 | R23: 204
P24: 15m Van Mount (Up to 3 Days) | Q24: 3 | R24: 408
P25: 15m Van Mount (Up to 5 Days) | Q25: 4 | R25: 612
P26: Other (Manually enter cost below) | Q26: 5 | R26: 0

Sheet ACCESS
F2: SLR | G2: Travel | H2: Visits | I2: MinPrice
F3: 77 | G3: 20 | H3: 1 | I3: 99
A4: =F3 -> 77 | B4: =G3 -> 20 | C4: =H3 -> 1
A6: ACCESS CONTROL MAINTENANCE CALCULATOR
F7: Pricing | K7: LABOUR MARGIN
A8: Site ID | B8: Site Name | C8: Access Control Server | D8: Access Controlled Door | E8: Intercom Door Station | F8: Standard ACCESS CONTROL Maintenance Fee | G8: Out of Hours Working Required ENTER "1" Below if REQ'D | I8: TOTAL TO QUOTE | K8: =1-(OVERVIEW!K5/ACCESS!F3) -> 0.59831169
A9: =OVERVIEW!B2 -> 0 | B9: =OVERVIEW!B1 -> 0 | C9: 0 | D9: 0 | E9: 0 | F9: =IF(SUM(C9:E9)=0,(0),IF((((C9*C10*A4+D9*D10*A4+E9*E10*A4)+(G3/60*F3))*H3)<I3,(I3),(((C9*C10*A4+D9*D10*A4+E9*E10*A4)+(G3/60*F3))*H3))) -> 0 | G9: 0 | I9: =H12 -> 0
C10: 0.5 | D10: 0.33 | E10: 0.25 | G10: 0.5
G11: =F9*G10*G9 -> 0
H12: =F9+G11 -> 0
A14: NOTES:

Sheet DAMPERS
E2: SLR* | F2: Travel | G2: Visits | H2: MinPrice | I2: ADJUST>> | J2: 30 | K2: Anticipated Mechanical Dampers per Day Tested | P2: =J2/7.5 -> 4 | Q2: M dampers per Hour | S2: =E3/P2 -> 26 | T2: per mechanical damper
D3: *2 Man CDO Team Rate | E3: 104 | F3: 20 | G3: 1 | H3: 149 | I3: ADJUST>> | J3: 25 | K3: Anticipated Automatic Dampers per Day Tested | P3: =J3/7.5 -> 3.3333333 | Q3: A dampers per Hour | S3: =E3/P3 -> 31.2 | T3: per automatic damper
A4: =E3 -> 104 | B4: =F3 -> 20 | C4: =G3 -> 1
A6: FIRE & SMOKE DAMPER MAINTENANCE CALCULATOR
E7: Pricing | J7: LABOUR MARGIN
A8: Site ID | B8: Site Name | C8: Mechanical Damper | D8: Automatic Damper | E8: Annual DAMPER Maintenance Fee | F8: Out of Hours Working Required ENTER "1" Below if REQ'D | G8: Enter Access Equipment COST Below | H8: Total to Quote | J8: =1-2*OVERVIEW!K6/DAMPERS!E3 -> 0.50096154
A9: =OVERVIEW!B2 -> 0 | B9: =OVERVIEW!B1 -> 0 | C9: 0 | D9: 0 | E9: =IF(SUM(C9:D9)=0,(0),IF((((C9*C10*A4+D9*D10*A4)+(F3/60*E3))*G3)<H3,(H3),(((C9*C10*A4+D9*D10*A4)+(F3/60*E3))*G3))) -> 0 | F9: 0 | G9: 0 | H9: =G12 -> 0
C10: =1/P2 -> 0.25 | D10: =1/P3 -> 0.3 | F10: 0.5 | G10: 1.25
F11: =E9*F10*F9 -> 0 | G11: =G10*G9 -> 0
F12: TOTAL TO QUOTE: | G12: =E9+F11+G11 -> 0
A14: NOTES:
G19: 194.63 | H19: cost per man per day
G20: =G19*2 -> 389.26 | H20: cost per team per day
G21: 130 | H21: team SLR/hour
G22: =G21*7.5 -> 975 | H22: team SLR/day
G24: =1-G20/G22 -> 0.60075897 | H24: margin

Sheet MONITORING
A1: REMOTE MONITORING CALCULATOR
D2: Digi | E2: RedCare | J2: Emizon | M2: DualCom | Q2: Pricing | V2: MONITORING MARGIN
A3: Site ID | B3: Site Name | C3: System | D3: Digital Communicator | E3: RedCare Classic - Grade 4 | F3: RedCare Secure - Grade 2 | G3: RedCare Secure - Grade 3 | H3: RedCare Secure - Grade 4 | I3: RedCare GSM - Grade 4 | J3: Emizon IP - Grade 2 | K3: Emizon IP - Grade 3 | L3: Emizon IP - Grade 4 | M3: DualCom DigiAIR - Grade 2 | N3: DualCom GPRS - Grade 2 | O3: DualCom GPRS - Grade 3 | P3: DualCom GPRS - Grade 4 | Q3: Standard Annual Monitoring Fee | T3: Total to Quote | V3: =IF($Q$4+$T$11=0,"0%",1-(($Q$6+$Q$9+$Q$11)/($Q$5+$Q$8+$T$11))) -> 0% | Y3: =IF($Q$4+$Q$7+$T$11=0,"0%",1-(($Q$6+$Q$9+$Q$11)/(OVERVIEW!E18+OVERVIEW!E19+OVERVIEW!E20))) -> 0%
A4: =OVERVIEW!B2 -> 0 | B4: =OVERVIEW!B1 -> 0 | C4: Fire Alarm | D4: 0 | E4: 0 | F4: 0 | G4: 0 | H4: 0 | I4: 0 | J4: 0 | K4: 0 | L4: 0 | M4: 0 | N4: 0 | O4: 0 | P4: 0 | Q4: =Q5 -> 0 | T4: =Q4 -> 0
C5: Sell | D5: =D4*T23 -> 0 | E5: =E4*T24 -> 0 | F5: =F4*T25 -> 0 | G5: =G4*T26 -> 0 | H5: =H4*T27 -> 0 | I5: =I4*T28 -> 0 | J5: =J4*T29 -> 0 | K5: =K4*T30 -> 0 | L5: =L4*T31 -> 0 | M5: =M4*T32 -> 0 | N5: =N4*T33 -> 0 | O5: =O4*T34 -> 0 | P5: =P4*T35 -> 0 | Q5: =SUM(D5:P5) -> 0 | T5: =S13 -> 0
C6: Cost | D6: =D4*S23 -> 0 | E6: =E4*S24 -> 0 | F6: =F4*S25 -> 0 | G6: =G4*S26 -> 0 | H6: =H4*S27 -> 0 | I6: =I4*S28 -> 0 | J6: =J4*S29 -> 0 | K6: =K4*S30 -> 0 | L6: =L4*S31 -> 0 | M6: =M4*S32 -> 0 | N6: =N4*S33 -> 0 | O6: =O4*S34 -> 0 | P6: =P4*S35 -> 0 | Q6: =SUM(D6:P6) -> 0 | T6: =S15 -> 0
C7: Intruder Alarm | D7: 0 | E7: 0 | F7: 0 | G7: 0 | H7: 0 | I7: 0 | J7: 0 | K7: 0 | L7: 0 | M7: 0 | N7: 0 | O7: 0 | P7: 0 | Q7: =Q8 -> 0 | T7: =Q7 -> 0
C8: Sell | D8: =D7*T23 -> 0 | E8: =E7*T24 -> 0 | F8: =F7*T25 -> 0 | G8: =G7*T26 -> 0 | H8: =H7*T27 -> 0 | I8: =I7*T28 -> 0 | J8: =J7*T29 -> 0 | K8: =K7*T30 -> 0 | L8: =L7*T31 -> 0 | M8: =M7*T32 -> 0 | N8: =N7*T33 -> 0 | O8: =O7*T34 -> 0 | P8: =P7*T35 -> 0 | Q8: =SUM(D8:P8) -> 0
C9: Cost | D9: =D7*S23 -> 0 | E9: =E7*S24 -> 0 | F9: =F7*S25 -> 0 | G9: =G7*S26 -> 0 | H9: =H7*S27 -> 0 | I9: =I7*S28 -> 0 | J9: =J7*S29 -> 0 | K9: =K7*S30 -> 0 | L9: =L7*S31 -> 0 | M9: =M7*S32 -> 0 | N9: =N7*S33 -> 0 | O9: =O7*S34 -> 0 | P9: =P7*S35 -> 0 | Q9: =SUM(D9:P9) -> 0 | R9: =Q4*R5*R4 -> 0 | S9: =S4*S5*Q4 -> 0
Q10: CCTV Monitoring Cost | S10: Margin (%) | T10: Sell
C11: CCTV | D11: Quotation to be requested from chosen RVRC | Q11: 0 | S11: 0.5 | T11: =Q11/(1-S11) -> 0
R12: TOTAL TO QUOTE: | S12: =T4+T7+T11 -> 0
A14: *** To monitor this Intruder Alarm System, the system must be maintained by Cormeton Electronics Ltd. Under current regulations we are unable to monitor systems which are not maintained or which are maintained by a 3rd party ***
A15: NOTES:
Q22: CASH Part No | R22: Description | S22: Cost | T22: Sell
Q23: B002 | R23: Digital Communicator | S23: 20 | T23: 99
Q24: B004 | R24: RedCare Classic - Grade 4 | S24: 197.64 | T24: 399
Q25: B004AG2R | R25: RedCare Secure - Grade 2 | S25: 98.4 | T25: 349
Q26: B004AG3R | R26: RedCare Secure - Grade 3 | S26: 124.8 | T26: 375
Q27: B007AGIP4R | R27: RedCare Secure - Grade 4 | S27: 119.4 | T27: 460
Q28: B004G4G | R28: RedCare GSM - Grade 4 | S28: 188.76 | T28: 460
Q29: B007EM2 | R29: Emizon IP - Grade 2 | S29: 97 | T29: 325
Q30: B007EM3 | R30: Emizon IP - Grade 3 | S30: 123 | T30: 350
Q31: B007EM4 | R31: Emizon IP - Grade 4 | S31: 149 | T31: 375
Q32: B013DIGA | R32: DualCom DigiAIR - Grade 2 | S32: 45 | T32: 150
Q33: B013GP2 | R33: DualCom GPRS - Grade 2 | S33: 89 | T33: 350
Q34: B013GP3 | R34: DualCom GPRS - Grade 3 | S34: 140 | T34: 395
Q35: B013GP4W | R35: DualCom GPRS - Grade 4 | S35: 199 | T35: 450
